{
  "mode": "multi",
  "scores_path": "data/zero_shot_bart_mnli_scores.csv",
  "data_path": "data/opiates_text_filtered.csv",
  "output_path": "data/opiates_claimtaxo_input_5labels_ge0.7.csv",
  "n_input": 158496,
  "n_kept": 17138,
  "n_dropped": 141358,
  "keep_rate": 0.10812891177064406,
  "thresholds": {
    "Factual_Claim": 0.7,
    "Evaluative_Opinion": 0.7,
    "Causal_Claim": 0.7,
    "Policy_Prescription": 0.7,
    "Argumentative_Reasoning": 0.7
  },
  "require_labels": [
    "Factual_Claim",
    "Evaluative_Opinion",
    "Causal_Claim",
    "Policy_Prescription",
    "Argumentative_Reasoning"
  ],
  "kept_selected_label_counts": {
    "Causal_Claim": 9363,
    "Evaluative_Opinion": 8045,
    "Policy_Prescription": 6209,
    "Factual_Claim": 2555,
    "Argumentative_Reasoning": 868
  }
}